gpurun/__init__.py
gpurun/cli.py
gpurun-0.1.1.dist-info/METADATA
gpurun-0.1.1.dist-info/WHEEL
gpurun-0.1.1.dist-info/entry_points.txt
gpurun-0.1.1.dist-info/licenses/LICENSE.txt
gpurun-0.1.1.dist-info/RECORD
