Metadata-Version: 2.3
Name: gpurun
Version: 0.1.1
Summary: GPU job scheduler using filelock
Project-URL: Homepage, https://github.com/zhou13/gpurun
Project-URL: Issues, https://github.com/zhou13/gpurun/issues
Author-email: Yichao Zhou <yichao.zhou@apple.com>
Classifier: License :: OSI Approved :: MIT License
Classifier: Operating System :: OS Independent
Classifier: Programming Language :: Python :: 3
Requires-Python: >=3.7
Requires-Dist: filelock>=3.16.1
